setup.py
algogd/__init__.py
algogd.egg-info/PKG-INFO
algogd.egg-info/SOURCES.txt
algogd.egg-info/dependency_links.txt
algogd.egg-info/not-zip-safe
algogd.egg-info/requires.txt
algogd.egg-info/top_level.txt