Metadata-Version: 1.0
Name: algogd
Version: 0.1
Summary: Algorithmic backtester for incorporating GDELT event data into finance analysis
Home-page: http://github.com/nkarnik/algogd
Author: Nikhil Karnik
Author-email: n.karnik@yahoo.com
License: MIT
Platform: UNKNOWN
